python_benforder/__init__.py
python_benforder/cli.py
python_benforder/python_benforder.py
python_benforder-0.2.0.dist-info/LICENSE
python_benforder-0.2.0.dist-info/METADATA
python_benforder-0.2.0.dist-info/WHEEL
python_benforder-0.2.0.dist-info/entry_points.txt
python_benforder-0.2.0.dist-info/top_level.txt
python_benforder-0.2.0.dist-info/RECORD
