Metadata-Version: 2.1
Name: python-benforder
Version: 0.2.0
Summary: A small python CLI tool to check the bendfordness of a bunch of numbers
Home-page: https://github.com/wakaru44/python_benforder
Author: Wakaru Himura
Author-email: wakaru44@gmail.com
License: GNU General Public License v3
Keywords: python_benforder
Platform: UNKNOWN
Classifier: Development Status :: 2 - Pre-Alpha
Classifier: Intended Audience :: Developers
Classifier: License :: OSI Approved :: GNU General Public License v3 (GPLv3)
Classifier: Natural Language :: English
Classifier: Programming Language :: Python :: 3
Classifier: Programming Language :: Python :: 3.5
Classifier: Programming Language :: Python :: 3.6
Classifier: Programming Language :: Python :: 3.7
Classifier: Programming Language :: Python :: 3.8
Requires-Python: >=3.5
